phepy/__init__.py
phepy/detector.py
phepy/plot.py
phepy/toys/__init__.py
phepy/toys/circle.py
phepy/toys/haystack.py
phepy/toys/line.py
phepy-0.1.0.dist-info/LICENSE-APACHE
phepy-0.1.0.dist-info/LICENSE-MIT
phepy-0.1.0.dist-info/METADATA
phepy-0.1.0.dist-info/WHEEL
phepy-0.1.0.dist-info/top_level.txt
phepy-0.1.0.dist-info/RECORD
