Metadata-Version: 2.1
Name: phepy
Version: 0.1.0
Summary: Intuitive evaluation of out-of-distribution detectors using simple toy examples.
Author-email: Juniper Tyree <juniper.tyree@helsinki.fi>
Maintainer-email: Juniper Tyree <juniper.tyree@helsinki.fi>
License: Apache License
Requires-Python: >=3.7
License-File: LICENSE-APACHE
License-File: LICENSE-MIT
Requires-Dist: matplotlib (>=3.0)
Requires-Dist: numpy (>=1.0)
Provides-Extra: dev
Requires-Dist: black ; extra == 'dev'
Requires-Dist: build ; extra == 'dev'
Requires-Dist: bumpver ; extra == 'dev'
Requires-Dist: pyproject-flake8 ; extra == 'dev'
Requires-Dist: isort ; extra == 'dev'
Requires-Dist: twine ; extra == 'dev'
Provides-Extra: example
Requires-Dist: jupyter ; extra == 'example'
Requires-Dist: sklearn ; extra == 'example'
